Workbook

Sheet FY2027_Budget_Model
A1: Line_ID | B1: Division_ID | C1: Division_Name | D1: Fund_Type | E1: Cost_Center | F1: Line_Item_Name | G1: Expense_Category | H1: P12M_Recurring_NIU | I1: TTM_Excluded_One_Off_NIU | J1: TTM_Recurring_NIU | K1: YoY_Growth_Pct | L1: Baseline_Growth_Driver_Pct | M1: Rough_Budget_NIU | N1: Recommended_Adjustment_Pct | O1: Final_Budget_NIU | P1: Cross_Fund_Transfer_NIU | Q1: Ring_Fenced_Flag | R1: Analyst_Override_Flag | S1: Review_Disposition | T1: Analyst_Commentary
A2: LI-01 | B2: DIV-A | C2: Division A — Core Platform | D2: OPERATING | E2: CC-101 | F2: Platform Core Compute Clusters | G2: Contractual Infrastructure | H2: 504 | I2: 0 | J2: 531.71 | K2: 5.5 | L2: 5.62 | M2: 561.59 | N2: 0 | O2: 561.59 | P2: 0 | Q2: FALSE | R2: UNLOCKED | S2: PROTECTED_NO_CUT | T2: ADR-0003 enforced: Contractual Infrastructure is protected from automated percentage compression (0.00% cut). [Pass 2 re-run: +1.50% macro driver update applied]
A3: LI-02 | B3: DIV-A | C3: Division A — Core Platform | D3: OPERATING | E3: CC-102 | F3: Observability & Telemetry SaaS | G3: Contractual Infrastructure | H3: 221.99 | I3: 0 | J3: 235.33 | K3: 6.01 | L3: 6.01 | M3: 249.47 | N3: 0 | O3: 249.47 | P3: 0 | Q3: FALSE | R3: UNLOCKED | S3: PROTECTED_NO_CUT | T3: ADR-0003 enforced: Contractual Infrastructure is protected from automated percentage compression (0.00% cut). [Pass 2 re-run: +1.50% macro driver update applied]
A4: LI-03 | B4: DIV-A | C4: Division A — Core Platform | D4: OPERATING | E4: CC-103 | F4: Product Engineering Compensation | G4: Personnel & Compensation | H4: 1140 | I4: 0 | J4: 1191.28 | K4: 4.5 | L4: 3.5 | M4: 1232.97 | N4: 2.5 | O4: 1246.8 | P4: 0 | Q4: FALSE | R4: LOCKED | S4: HUMAN_LOCKED_APPROVED | T4: Locked per VP Engineering sign-off: retains 2 principal systems architects for Q2 platform migration.
A5: LI-04 | B5: DIV-A | C5: Division A — Core Platform | D5: OPERATING | E5: CC-104 | F5: Developer Sandbox Cloud Burst | G5: Discretionary Opex | H5: 192 | I5: 0 | J5: 214.08 | K5: 11.5 | L5: 8.4 | M5: 232.06 | N5: -12 | O5: 204.21 | P5: 0 | Q5: FALSE | R5: UNLOCKED | S5: TIER_1_MAX_CAP_CUT | T5: ADR-0003 Tier 1 compression (-12.00% cap) triggered by TTM YoY growth >= +8.00%. [Pass 2 re-run: +1.50% macro driver update applied]
A6: LI-05 | B6: DIV-A | C6: Division A — Core Platform | D6: OPERATING | E6: CC-105 | F6: SOC2 & ISO Security Audits | G6: Regulatory Compliance | H6: 132 | I6: 0 | J6: 136.64 | K6: 3.52 | L6: 3.96 | M6: 142.05 | N6: 0 | O6: 142.05 | P6: 0 | Q6: FALSE | R6: UNLOCKED | S6: PROTECTED_NO_CUT | T6: ADR-0003 enforced: Regulatory Compliance is protected from automated percentage compression (0.00% cut). [Pass 2 re-run: +1.50% macro driver update applied]
A7: LI-06 | B7: DIV-A | C7: Division A — Core Platform | D7: OPERATING | E7: CC-106 | F7: External UI/UX Prototyping Studio | G7: Discretionary Opex | H7: 168 | I7: 0 | J7: 183.95 | K7: 9.49 | L7: 7.19 | M7: 197.18 | N7: -12 | O7: 173.52 | P7: 0 | Q7: FALSE | R7: UNLOCKED | S7: TIER_1_MAX_CAP_CUT | T7: ADR-0003 Tier 1 compression (-12.00% cap) triggered by TTM YoY growth >= +8.00%. [Pass 2 re-run: +1.50% macro driver update applied]
A8: LI-07 | B8: DIV-A | C8: Division A — Core Platform | D8: OPERATING | E8: CC-107 | F8: API Gateway Bandwidth Commit | G8: Contractual Infrastructure | H8: 288 | I8: 0 | J8: 302.4 | K8: 5 | L8: 3.75 | M8: 313.74 | N8: -4 | O8: 298.5 | P8: 0 | Q8: FALSE | R8: LOCKED | S8: HUMAN_LOCKED_APPROVED | T8: Locked per negotiated multi-year bandwidth addendum signed 2026-09-14.
A9: LI-08 | B9: DIV-A | C9: Division A — Core Platform | D9: OPERATING | E9: CC-108 | F9: Technical Documentation Contractors | G9: Discretionary Opex | H9: 114.01 | I9: 120 | J9: 119.16 | K9: 4.52 | L9: 4.21 | M9: 124.18 | N9: -6.5 | O9: 116.11 | P9: 0 | Q9: FALSE | R9: UNLOCKED | S9: TIER_2_MODERATE_CUT | T9: ADR-0003 Tier 2 compression (-6.50%) triggered by TTM YoY growth in [+3.00%, +8.00%). [Pass 2 re-run: +1.50% macro driver update applied]
A10: LI-09 | B10: DIV-A | C10: Division A — Core Platform | D10: OPERATING | E10: CC-109 | F10: Quality Assurance Automation Lab | G10: Discretionary Opex | H10: 144 | I10: 0 | J10: 146.88 | K10: 2 | L10: 3.5 | M10: 152.02 | N10: -3 | O10: 147.46 | P10: 0 | Q10: FALSE | R10: UNLOCKED | S10: TIER_3_BASELINE_TRIM | T10: ADR-0003 Tier 3 baseline efficiency trim (-3.00%) applied to low-growth Discretionary Opex. [Pass 2 re-run: +1.50% macro driver update applied]
A11: LI-10 | B11: DIV-A | C11: Division A — Core Platform | D11: OPERATING | E11: CC-110 | F11: Site Reliability Engineering Payroll | G11: Personnel & Compensation | H11: 816 | I11: 0 | J11: 848.65 | K11: 4 | L11: 5 | M11: 891.08 | N11: 0 | O11: 891.08 | P11: 0 | Q11: FALSE | R11: UNLOCKED | S11: ROUTED_TO_HEADCOUNT_SCENARIO | T11: ADR-0003 enforced: Personnel & Compensation routed to executive headcount scenario modeling. [Pass 2 re-run: +1.50% macro driver update applied]
A12: LI-11 | B12: DIV-B | C12: Division B — Field Operations | D12: OPERATING | E12: CC-201 | F12: Regional Commercial Account Payroll | G12: Personnel & Compensation | H12: 1056 | I12: 0 | J12: 1108.79 | K12: 5 | L12: 5 | M12: 1164.23 | N12: 0 | O12: 1164.23 | P12: 0 | Q12: FALSE | R12: UNLOCKED | S12: ROUTED_TO_HEADCOUNT_SCENARIO | T12: ADR-0003 enforced: Personnel & Compensation routed to executive headcount scenario modeling. [Pass 2 re-run: +1.50% macro driver update applied]
A13: LI-12 | B13: DIV-B | C13: Division B — Field Operations | D13: OPERATING | E13: CC-202 | F13: Trade Show Pavilions | G13: Discretionary Opex | H13: 264 | I13: 0 | J13: 296.99 | K13: 12.5 | L13: 7.5 | M13: 319.26 | N13: -8.5 | O13: 286.4 | P13: 0 | Q13: FALSE | R13: LOCKED | S13: HUMAN_LOCKED_APPROVED | T13: Locked by Field Ops Controller: flagship Q3 commercial summit booth deposit already contracted.
... A37: LI-36 | B37: DIV-R | C37: Designated R&D Reserve | D37: DESIGNATED_RESERVE | E37: CC-906 | F37: University Research Grant Consortium | G37: Designated R&D Reserve | H37: 197.99 | I37: 0 | J37: 205.92 | K37: 4.01 | L37: 5 | M37: 216.22 | N37: 0 | O37: 216.22 | P37: 0 | Q37: TRUE | R37: UNLOCKED | S37: RING_FENCED_NO_SWEEP | T37: ADR-0002 enforced: Designated R&D Reserve is ring-fenced from operating compression sweeps. [Pass 2 re-run: +1.50% macro driver update applied]
A38: TOTAL_PORTFOLIO | B38: ALL | C38: Total (Operating + Ring-Fenced Reserve) | D38: CONSOLIDATED | E38: ALL_CC | F38: All 36 Cost-Center Line Items | G38: ALL_CATEGORIES | H38: =SUM(H2:H37) | I38: =SUM(I2:I37) | J38: =SUM(J2:J37) | K38: =AVERAGE(K2:K37) | L38: =AVERAGE(L2:L37) | M38: =SUM(M2:M37) | N38: =AVERAGE(N2:N37) | O38: =SUM(O2:O37) | P38: =SUM(P2:P37) | Q38: MIXED | R38: GOVERNED | S38: PORTFOLIO_TOTAL | T38: Live Excel formula roll-up verified by Governance Auditor.

Sheet Executive_Summary
A1: Governance_Pool_ID | B1: Division_Or_Pool_Name | C1: Fund_Type | D1: Line_Item_Count | E1: P12M_Recurring_NIU | F1: TTM_Recurring_NIU | G1: Rough_Budget_NIU | H1: Final_Budget_NIU | I1: Cross_Fund_Transfer_NIU | J1: ADR_0002_Ring_Fence_Status
A2: DIV-A | B2: Division A — Core Platform | C2: OPERATING | D2: =COUNTIF(FY2027_Budget_Model!B2:B37,"DIV-A") | E2: =SUMIF(FY2027_Budget_Model!B2:B37,"DIV-A",FY2027_Budget_Model!H2:H37) | F2: =SUMIF(FY2027_Budget_Model!B2:B37,"DIV-A",FY2027_Budget_Model!J2:J37) | G2: =SUMIF(FY2027_Budget_Model!B2:B37,"DIV-A",FY2027_Budget_Model!M2:M37) | H2: =SUMIF(FY2027_Budget_Model!B2:B37,"DIV-A",FY2027_Budget_Model!O2:O37) | I2: =SUMIF(FY2027_Budget_Model!B2:B37,"DIV-A",FY2027_Budget_Model!P2:P37) | J2: OPERATING_POOL_ELIGIBLE
A3: DIV-B | B3: Division B — Field Operations | C3: OPERATING | D3: =COUNTIF(FY2027_Budget_Model!B2:B37,"DIV-B") | E3: =SUMIF(FY2027_Budget_Model!B2:B37,"DIV-B",FY2027_Budget_Model!H2:H37) | F3: =SUMIF(FY2027_Budget_Model!B2:B37,"DIV-B",FY2027_Budget_Model!J2:J37) | G3: =SUMIF(FY2027_Budget_Model!B2:B37,"DIV-B",FY2027_Budget_Model!M2:M37) | H3: =SUMIF(FY2027_Budget_Model!B2:B37,"DIV-B",FY2027_Budget_Model!O2:O37) | I3: =SUMIF(FY2027_Budget_Model!B2:B37,"DIV-B",FY2027_Budget_Model!P2:P37) | J3: OPERATING_POOL_ELIGIBLE
A4: DIV-C | B4: Division C — Shared Services | C4: OPERATING | D4: =COUNTIF(FY2027_Budget_Model!B2:B37,"DIV-C") | E4: =SUMIF(FY2027_Budget_Model!B2:B37,"DIV-C",FY2027_Budget_Model!H2:H37) | F4: =SUMIF(FY2027_Budget_Model!B2:B37,"DIV-C",FY2027_Budget_Model!J2:J37) | G4: =SUMIF(FY2027_Budget_Model!B2:B37,"DIV-C",FY2027_Budget_Model!M2:M37) | H4: =SUMIF(FY2027_Budget_Model!B2:B37,"DIV-C",FY2027_Budget_Model!O2:O37) | I4: =SUMIF(FY2027_Budget_Model!B2:B37,"DIV-C",FY2027_Budget_Model!P2:P37) | J4: OPERATING_POOL_ELIGIBLE
A5: SUBTOTAL-OP | B5: Operating Divisions Subtotal (DIV-A + DIV-B + DIV-C) | C5: OPERATING_POOL | D5: =SUM(D2:D4) | E5: =SUM(E2:E4) | F5: =SUM(F2:F4) | G5: =SUM(G2:G4) | H5: =SUM(H2:H4) | I5: =SUM(I2:I4) | J5: COMMERCIAL_OPERATING_POOL
A6: DIV-R | B6: Designated R&D Reserve (Ring-Fenced Pool) | C6: DESIGNATED_RESERVE | D6: =COUNTIF(FY2027_Budget_Model!B2:B37,"DIV-R") | E6: =SUMIF(FY2027_Budget_Model!B2:B37,"DIV-R",FY2027_Budget_Model!H2:H37) | F6: =SUMIF(FY2027_Budget_Model!B2:B37,"DIV-R",FY2027_Budget_Model!J2:J37) | G6: =SUMIF(FY2027_Budget_Model!B2:B37,"DIV-R",FY2027_Budget_Model!M2:M37) | H6: =SUMIF(FY2027_Budget_Model!B2:B37,"DIV-R",FY2027_Budget_Model!O2:O37) | I6: =SUMIF(FY2027_Budget_Model!B2:B37,"DIV-R",FY2027_Budget_Model!P2:P37) | J6: STRICTLY_RING_FENCED_ADR_0002
A7: TOTAL-ENT | B7: Consolidated Portfolio (Operating + Reserve) | C7: CONSOLIDATED | D7: =D5+D6 | E7: =E5+E6 | F7: =F5+F6 | G7: =G5+G6 | H7: =H5+H6 | I7: =I5+I6 | J7: ZERO_CROSS_FUND_SWEEP_VERIFIED

Sheet ADR_Audit_Trail
A1: ADR_ID | B1: Policy_Title | C1: Enforcement_Stage | D1: Target_Scope | E1: Verification_Status | F1: Audit_Evidence_Summary
A2: ADR-0001 | B2: TTM Seasonal Baseline and One-Off Exclusion | C2: Stage 1 & Stage 2 | D2: 36 Cost Centers (24M Window) | E2: ENFORCED | F2: 4 one-off capital spikes (410.00 NIU total; 315.00 NIU in TTM) stripped from recurring baseline.
A3: ADR-0002 | B3: Ring-Fenced Designated Reserve Transfers | C3: Stage 3 & Stage 4 | D3: DIV-R (CC-901..CC-906) | E3: ENFORCED | F3: 6 Designated R&D Reserve lines segregated with 0.00 NIU cross-fund operating sweeps.
A4: ADR-0003 | B4: Tiered Opex Compression and Protected Lines | C4: Stage 4 (Pass 1 & Pass 2) | D4: 29 Unlocked Line Items | E4: ENFORCED | F4: Discretionary cuts capped at -12.00%; Contractual Infrastructure & Compliance held at 0.00% cut; Personnel routed to Headcount Scenario.
A5: ADR-0004 | B5: Non-Destructive Human Override Preservation | C5: Stage 4 (Pass 2 Re-Run) | D5: 7 Locked Human Analyst Overrides | E5: ENFORCED | F5: 7/7 LOCKED rows preserved 100% verbatim across +1.50% macro re-run; 29/29 UNLOCKED rows dynamically recalculated.
